pythonopensubtitles/__init__.py
pythonopensubtitles/opensubtitles.py
pythonopensubtitles/settings.py
pythonopensubtitles/test_opensubtitles.py
pythonopensubtitles/test_utils.py
pythonopensubtitles/utils.py
python_opensubtitles-0.6.dev0.dist-info/LICENSE
python_opensubtitles-0.6.dev0.dist-info/METADATA
python_opensubtitles-0.6.dev0.dist-info/WHEEL
python_opensubtitles-0.6.dev0.dist-info/top_level.txt
python_opensubtitles-0.6.dev0.dist-info/RECORD
