Metadata-Version: 2.1
Name: python-opensubtitles
Version: 0.6.dev0
Summary: Wrapper to use the OpenSubtitles API easily
Home-page: http://twitter.com/agonzalezro
Author: Ãlex GonzÃ¡lez
Author-email: agonzalezro@gmail.com
License: BSD
Keywords: opensubtitles python api
Platform: UNKNOWN
Provides-Extra: support_for_encoding_detection_on_downloaded_subtitle
Requires-Dist: charset-normalizer ; extra == 'support_for_encoding_detection_on_downloaded_subtitle'
